[{"employee_name":"Rama Krishna","employee_department":"DevOps Engineer","employee_phonenumber":9876543219,"employee_office_branch":"Hyderabad"},{"employee_name":"RamaKiran","employee_department":"Full Stack Developer","employee_phonenumber":7656789876,"employee_office_branch":"Hyderabad"},{"employee_name":"Ramsai","employee_department":"Full Stack Developer","employee_phonenumber":7698789876,"employee_office_branch":"Banglore"},{"employee_name":"Ramanjenaya","employee_department":"Full Stack Developer","employee_phonenumber":7698789876,"employee_office_branch":"Banglore"}]
